nft_sdk-2.2.0.2-py3.7-nspkg.pth
github/com/__init__.py
github/com/gogo/__init__.py
github/com/gogo/protobuf/__init__.py
github/com/gogo/protobuf/gogoproto/__init__.py
github/com/gogo/protobuf/gogoproto/gogo_pb2.py
google/api/__init__.py
google/api/annotations_pb2.py
google/api/http_pb2.py
nf/__version__.py
nf/callback.py
nf/constant.py
nf/enum.py
nf/pb_to_dict.py
nf/utils.py
nf/api/__init__.py
nf/api/basic.py
nf/api/query.py
nf/api/strategies.py
nf/api/trade.py
nf/csdk/__init__.py
nf/csdk/c_sdk.cp37-win_amd64.pyd
nf/csdk/nf-sdk-c.dll
nf/csdk/setup.py
nf/model/__init__.py
nf/model/account.py
nf/model/storage.py
nf/model/storage_data.py
nf/model/sub.py
nf/pb/__init__.py
nf/pb/auth/api/auth/service_pb2.py
nf/pb/core/api/account_pb2.py
nf/pb/core/api/common_pb2.py
nf/pb/core/api/report/service_pb2.py
nf/pb/data/api/data_pb2.py
nf/pb/gogoproto/gogo_pb2.py
nf/pb/strategy/api/strategy_pb2.py
nf/pb/strategy/api/strategy/service_pb2.py
nf/pb/strategy/strategy_params/strategy/__init__.py
nf/pb/strategy/strategy_params/strategy/params_pb2.py
nf/pb/trade/api/trade/service_pb2.py
nf/pb/tradegw/api/tradegw/service_pb2.py
third_lib/TA_Lib-0.4.17-cp37-cp37m-win_amd64.whl
nft_sdk-2.2.0.2.dist-info/METADATA
nft_sdk-2.2.0.2.dist-info/WHEEL
nft_sdk-2.2.0.2.dist-info/namespace_packages.txt
nft_sdk-2.2.0.2.dist-info/top_level.txt
nft_sdk-2.2.0.2.dist-info/RECORD
