Metadata-Version: 2.1
Name: nft-sdk
Version: 2.2.0.2
Summary: NextFintech sdk
Home-page: https://nextFintech.io/
Author: NextFintech
Author-email: support@NextFintech.com
License: Apache 2.0
Platform: UNKNOWN
Classifier: Programming Language :: Python :: 3.6
Classifier: Programming Language :: Python :: 3.7
Requires-Python: >=2.7, !=3.0.*, !=3.1.*, !=3.2.*, !=3.3.*, !=3.4.*, !=3.5.*, <4
Requires-Dist: typing (>=3.6.2)
Requires-Dist: arrow (>=0.12.1)
Requires-Dist: grpcio (>=1.14.2)
Requires-Dist: Cython (>=0.26.1)
Requires-Dist: protobuf (>=3.6.0)
Provides-Extra: pandas
Requires-Dist: pandas ; extra == 'pandas'
